spiceypy-7.0.0.dist-info/RECORD
spiceypy-7.0.0.dist-info/WHEEL
spiceypy-7.0.0.dist-info/METADATA
spiceypy-7.0.0.dist-info/licenses/LICENSE
spiceypy/config.py
spiceypy/spiceypy.py
spiceypy/found_catcher.py
spiceypy/__init__.py
spiceypy/tests/test_gettestkernels.py
spiceypy/tests/test_support_types.py
spiceypy/tests/test_wrapper.py
spiceypy/tests/__init__.py
spiceypy/tests/test_context_manager.py
spiceypy/tests/gettestkernels.py
spiceypy/tests/test_spiceerrors.py
spiceypy/utils/libspicehelper.py
spiceypy/utils/support_types.py
spiceypy/utils/__init__.py
spiceypy/utils/callbacks.py
spiceypy/utils/exceptions.py
spiceypy/utils/libcspice.dylib
spiceypy/benchmarks/test_cyice.py
spiceypy/benchmarks/__init__.py
spiceypy/cyice/cyice.pxd
spiceypy/cyice/__init__.py
spiceypy/cyice/cyice.cpython-310-darwin.so
spiceypy/cyice/cyice.pyx
