Metadata-Version: 2.4
Name: spiceypy
Version: 7.0.0
Summary: A Python Wrapper for the NAIF CSPICE Toolkit
Keywords: spiceypy,spice,cspice,naif,jpl,space,geometry,ephemeris
Author-Email: "Andrew M. annex" <ama6fy@virginia.edu>
Maintainer-Email: "Andrew M. annex" <ama6fy@virginia.edu>
License-Expression: MIT
License-File: LICENSE
Classifier: Development Status :: 5 - Production/Stable
Classifier: Natural Language :: English
Classifier: Topic :: Scientific/Engineering
Classifier: Topic :: Scientific/Engineering :: Astronomy
Classifier: Programming Language :: Python :: 3 :: Only
Classifier: Programming Language :: Python :: 3.10
Classifier: Programming Language :: Python :: 3.11
Classifier: Programming Language :: Python :: 3.12
Classifier: Programming Language :: Python :: 3.13
Classifier: Programming Language :: Cython
Classifier: Operating System :: MacOS :: MacOS X
Classifier: Operating System :: POSIX :: Linux
Classifier: Operating System :: POSIX :: BSD :: FreeBSD
Classifier: Operating System :: Microsoft :: Windows
Project-URL: Homepage, https://github.com/AndrewAnnex/SpiceyPy
Project-URL: Repository, https://github.com/AndrewAnnex/SpiceyPy
Project-URL: Source, https://github.com/AndrewAnnex/SpiceyPy
Project-URL: Conda-Forge, https://anaconda.org/conda-forge/spiceypy
Project-URL: Documentation, https://spiceypy.readthedocs.io
Project-URL: Bug Tracker, https://github.com/AndrewAnnex/SpiceyPy/issues
Project-URL: Changelog, https://github.com/AndrewAnnex/SpiceyPy/blob/main/CHANGELOG.md
Requires-Python: >=3.10
Requires-Dist: numpy>=1.23.5
